zashcore/log.py
zashcore-0.3.0.dist-info/WHEEL
zashcore-0.3.0.dist-info/METADATA
zashcore-0.3.0.dist-info/RECORD
