Metadata-Version: 2.1
Name: zashcore
Version: 0.3.0
Summary: Core libs for zash
Author: Efe
Author-email: efe@joinzash.com
Requires-Python: >=3.9,<4.0
Classifier: Programming Language :: Python :: 3
Classifier: Programming Language :: Python :: 3.9
Classifier: Programming Language :: Python :: 3.10
Classifier: Programming Language :: Python :: 3.11
Requires-Dist: structlog (>=22.2.0,<23.0.0)
